README.rst
setup.py
testindata/TDA.py
testindata/__init__.py
testindata.egg-info/PKG-INFO
testindata.egg-info/SOURCES.txt
testindata.egg-info/dependency_links.txt
testindata.egg-info/entry_points.txt
testindata.egg-info/requires.txt
testindata.egg-info/top_level.txt
testindata/cli/__init__.py
testindata/cli/account.py
testindata/cli/cliUpload.py
testindata/cli/run.py
testindata/dataset/__init__.py
testindata/dataset/commitdb.py
testindata/dataset/dataset.py
testindata/dataset/file.py
testindata/dataset/labeldata.py
testindata/dataset/metadata.py
testindata/dataset/request.py
testindata/dataset/updatefile.py
testindata/dataset/uploaddb.py
testindata/dataset/urlfile.py
testindata/s3/__init__.py
testindata/s3/minio/__init__.py
testindata/s3/minio/minio.py
testindata/s3/qiniu/__init__.py
testindata/s3/qiniu/qiniu.py
testindata/utils/__init__.py
testindata/utils/util.py